Metadata-Version: 2.1
Name: vcetdspdcom
Version: 0.12
Summary: Basic Signal Processing algorithms and Communication Modulation techniques Package
Home-page: https://www.linkedin.com/in/shivaprasad-rao-a92b8219/
Author: Shivaprasad Rao
Author-email: shivarao101@gmail.com
License: UNKNOWN
Keywords: DSP DCOM
Platform: UNKNOWN
Classifier: Development Status :: 2 - Pre-Alpha
Classifier: Intended Audience :: Education
Classifier: License :: OSI Approved :: MIT License
Classifier: Natural Language :: English
Classifier: Operating System :: OS Independent
Classifier: Programming Language :: Python :: 3
Classifier: Topic :: Scientific/Engineering
Requires-Python: >=3.6
License-File: LICENSE.txt
